hario_core/__init__.py
hario_core/models/__init__.py
hario_core/models/extensions/__init__.py
hario_core/models/extensions/chrome_devtools.py
hario_core/models/har_1_2.py
hario_core/parse/__init__.py
hario_core/parse/har_parser.py
hario_core/parse/interfaces.py
hario_core/py.typed
hario_core/transform/__init__.py
hario_core/transform/defaults.py
hario_core/transform/interfaces.py
hario_core/transform/pipeline.py
hario_core/transform/strategies.py
hario_core/transform/transform.py
hario_core/transform/worker.py
hario_core-0.4.2.dist-info/LICENSE
hario_core-0.4.2.dist-info/METADATA
hario_core-0.4.2.dist-info/WHEEL
hario_core-0.4.2.dist-info/RECORD
