Metadata-Version: 2.3
Name: hario-core
Version: 0.4.2
Summary: Modern, type-safe, and extensible library for parsing, transforming, and analyzing HAR (HTTP Archive) files.
Keywords: har,http archive,pydantic,parsing,normalization,analytics,pipeline,transformers,deterministic id,devtools,extensible
Author: Vasiliy Pikulev
Author-email: pikulev.vasiliy@gmail.com
Requires-Python: >=3.10
Classifier: Development Status :: 4 - Beta
Classifier: Intended Audience :: Developers
Classifier: License :: OSI Approved :: MIT License
Classifier: Programming Language :: Python :: 3
Classifier: Programming Language :: Python :: 3.10
Classifier: Topic :: Internet :: Log Analysis
Classifier: Topic :: Software Development :: Libraries :: Python Modules
Classifier: Typing :: Typed
Provides-Extra: dev
Requires-Dist: black (==24.3.0) ; extra == "dev"
Requires-Dist: flake8 (==6.0.0) ; extra == "dev"
Requires-Dist: isort (==5.12.0) ; extra == "dev"
Requires-Dist: mkdocs (==1.6.0) ; extra == "dev"
Requires-Dist: mkdocs-autorefs (==0.5.0) ; extra == "dev"
Requires-Dist: mkdocs-material (==9.5.26) ; extra == "dev"
Requires-Dist: mkdocstrings[python] (==0.25.1) ; extra == "dev"
Requires-Dist: mypy (==1.7.1) ; extra == "dev"
Requires-Dist: orjson (==3.10.18)
Requires-Dist: pre-commit (==3.7.1) ; extra == "dev"
Requires-Dist: pydantic (>=2.5.0)
Requires-Dist: pydocstyle[toml] (==6.3.0) ; extra == "dev"
Requires-Dist: pytest (==8.2.2) ; extra == "dev"
Requires-Dist: pytest-cov ; extra == "dev"
Requires-Dist: rich (==13.9.4) ; extra == "dev"
Requires-Dist: snakeviz (==2.2.2) ; extra == "dev"
Requires-Dist: watchdog (==4.0.1) ; extra == "dev"
Project-URL: Bug Tracker, https://github.com/pikulev/hario-core/issues
Project-URL: Homepage, https://github.com/pikulev/hario-core
